fontprimer/__init__.py
fontprimer/colrguidelines.py
fontprimer/guidelines.py
fontprimer-0.2.2.dist-info/METADATA
fontprimer-0.2.2.dist-info/WHEEL
fontprimer-0.2.2.dist-info/top_level.txt
fontprimer-0.2.2.dist-info/RECORD
