Metadata-Version: 2.1
Name: fontprimer
Version: 0.2.2
Summary: A gftools-builder recipe provider for handwriting fonts
Author-email: Simon Cozens <simon@simon-cozens.org>
Requires-Dist: paintcompiler >=0.3.0
Requires-Dist: babelfont >=3.0.5
Requires-Dist: pendot >=0.1.1
